StructuralAnalysis/DegreeOfFreedom.py
StructuralAnalysis/Material.py
StructuralAnalysis/Node.py
StructuralAnalysis/Section.py
StructuralAnalysis/Solver.py
StructuralAnalysis/Structure.py
StructuralAnalysis/Visualization.py
StructuralAnalysis/__SolverHelper.py
StructuralAnalysis/__init__.py
StructuralAnalysis/__main__.py
StructuralAnalysis/FrameElements/Element.py
StructuralAnalysis/FrameElements/FrameElement.py
StructuralAnalysis/FrameElements/TrussElement.py
StructuralAnalysis/FrameElements/TwoDimensionalFrameElement.py
StructuralAnalysis/FrameElements/TwoDimensionalTrussElement.py
StructuralAnalysis/FrameElements/__init__.py
StructuralAnalysis-0.21.dist-info/METADATA
StructuralAnalysis-0.21.dist-info/WHEEL
StructuralAnalysis-0.21.dist-info/top_level.txt
StructuralAnalysis-0.21.dist-info/RECORD
