Metadata-Version: 2.1
Name: StructuralAnalysis
Version: 0.21
Summary: Package that performs structural analysis
Home-page: https://github.com/pypa/sampleproject
Author: Hazem Kassab
Author-email: Hazem_Kassab@hotmail.com
License: UNKNOWN
Platform: UNKNOWN
Classifier: Programming Language :: Python :: 3
Classifier: License :: OSI Approved :: MIT License
Classifier: Operating System :: OS Independent
Requires-Python: >=3.6
Requires-Dist: numpy (==1.19.5)
Requires-Dist: PyOpenGL (==3.1.5)
Requires-Dist: PyQt5 (==5.15.2)
Requires-Dist: pyqtgraph (==0.11.1)
